{
    "year": 2025,
    "month": 6,
    "theme": "False witnesses did rise up. Psalm 35:11",
    "verses": {
      "2025-06-01": "Bible Studies John 6:1-71",
      "2025-06-02": "Yona 2:4",
      "2025-06-03": "Yona 2:5",
      "2025-06-04": "Yona 2:6",
      "2025-06-05": "Yona 2:7",
      "2025-06-06": "Yona 2:8",
      "2025-06-07": "Prayer Night",
  
      "2025-06-08": "The Holy Spirit who brings salvation – Titus 3:5-7, Ephesians 1:13-14, Hebrews 12:2, 2 Corinthians 3:6",
      "2025-06-09": "Yona 2:9",
      "2025-06-10": "Yona 2:10",
      "2025-06-11": "Exodus 20:16",
      "2025-06-12": "1 Samuel 24:9",
      "2025-06-13": "1 Samuel 24:1",
      "2025-06-14": "Prayer Night",
  
      "2025-06-15": "He lifted the poor to sit on the higher throne of glory – 1 Samuel 7:8; 1 Samuel 2:8",
      "2025-06-16": "Psalm 59:1",
      "2025-06-17": "Psalm 59:2",
      "2025-06-18": "Psalm 59:3",
      "2025-06-19": "Psalm 59:4",
      "2025-06-20": "Psalm 59:5",
      "2025-06-21": "Prayer Night",
  
      "2025-06-22": "The heart is deceitful above all things – Jeremiah 17:9-11",
      "2025-06-23": "Psalm 59:6",
      "2025-06-24": "Psalm 59:7",
      "2025-06-25": "Psalm 59:8",
      "2025-06-26": "Psalm 59:9",
      "2025-06-27": "Psalm 59:10",
      "2025-06-28": "Prayer Night",
  
      "2025-06-29": "God did what Elisha asked – 2 Kings 2:9-15,23-24; 2 Kings 6:18; Matthew 7:7",
      "2025-06-30": "1 Samuel 24:12"
    }
  }